cybersploit/__init__.py
cybersploit/abstractClasses.py
cybersploit/clustering.py
cybersploit/matrix.py
cybersploit/sgd.py
cybersploit/testClustering.py
cybersploit/testMatrix.py
cybersploit/testSGD.py
cybersploit/testVector.py
cybersploit/vector.py
cybersploit-0.0.1.dist-info/LICENSE
cybersploit-0.0.1.dist-info/METADATA
cybersploit-0.0.1.dist-info/WHEEL
cybersploit-0.0.1.dist-info/top_level.txt
cybersploit-0.0.1.dist-info/RECORD
